nn_meter/__init__.py
nn_meter/builder/__init__.py
nn_meter/builder/config_manager.py
nn_meter/builder/nn_meter_builder.py
nn_meter/builder/utils.py
nn_meter/builder/backend_meta/__init__.py
nn_meter/builder/backend_meta/utils.py
nn_meter/builder/backend_meta/fusion_rule_tester/__init__.py
nn_meter/builder/backend_meta/fusion_rule_tester/build_tf_models.py
nn_meter/builder/backend_meta/fusion_rule_tester/build_torch_models.py
nn_meter/builder/backend_meta/fusion_rule_tester/generate_testcase.py
nn_meter/builder/backend_meta/fusion_rule_tester/interface.py
nn_meter/builder/backend_meta/fusion_rule_tester/test_fusion_rule.py
nn_meter/builder/backend_meta/fusion_rule_tester/utils.py
nn_meter/builder/backends/__init__.py
nn_meter/builder/backends/interface.py
nn_meter/builder/backends/openvino/__init__.py
nn_meter/builder/backends/openvino/openvino_backend.py
nn_meter/builder/backends/openvino/openvino_profiler.py
nn_meter/builder/backends/openvino/vpu.py
nn_meter/builder/backends/openvino/frozenpb_patcher/__init__.py
nn_meter/builder/backends/openvino/frozenpb_patcher/frozenpb_patcher.py
nn_meter/builder/backends/openvino/frozenpb_patcher/patcher_wrapper.py
nn_meter/builder/backends/openvino/utils/__init__.py
nn_meter/builder/backends/openvino/utils/converters.py
nn_meter/builder/backends/openvino/utils/restart.py
nn_meter/builder/backends/tflite/__init__.py
nn_meter/builder/backends/tflite/cpu.py
nn_meter/builder/backends/tflite/gpu.py
nn_meter/builder/backends/tflite/tflite_backend.py
nn_meter/builder/backends/tflite/tflite_profiler.py
nn_meter/builder/kernel_predictor_builder/__init__.py
nn_meter/builder/kernel_predictor_builder/data_sampler/__init__.py
nn_meter/builder/kernel_predictor_builder/data_sampler/config_sampler.py
nn_meter/builder/kernel_predictor_builder/data_sampler/finegrained_sampler.py
nn_meter/builder/kernel_predictor_builder/data_sampler/generator.py
nn_meter/builder/kernel_predictor_builder/data_sampler/prior_distribution_sampler.py
nn_meter-2.0.dist-info/LICENSE
nn_meter-2.0.dist-info/METADATA
nn_meter-2.0.dist-info/WHEEL
nn_meter-2.0.dist-info/entry_points.txt
nn_meter-2.0.dist-info/top_level.txt
nn_meter-2.0.dist-info/RECORD
