Metadata-Version: 2.1
Name: nn-meter
Version: 2.0
Summary: nn-Meter is a novel and efficient system to accurately predict the inference latency of DNN models on diverse edge devices.
Home-page: https://github.com/microsoft/nn-Meter
Author: Microsoft nn-Meter Team
Author-email: nn-meter-dev@microsoft.com
License: MIT
Project-URL: Data of models, https://github.com/microsoft/nn-Meter/releases/tag/v1.0-data
Platform: UNKNOWN
Classifier: License :: OSI Approved :: MIT License
Classifier: Operating System :: MacOS :: MacOS X
Classifier: Operating System :: Microsoft :: Windows :: Windows 10
Classifier: Operating System :: POSIX :: Linux
Classifier: Programming Language :: Python :: 3 :: Only
Classifier: Topic :: Scientific/Engineering :: Artificial Intelligence
License-File: LICENSE
Requires-Dist: numpy
Requires-Dist: pandas
Requires-Dist: tqdm
Requires-Dist: networkx
Requires-Dist: requests
Requires-Dist: protobuf
Requires-Dist: PyYAML
Requires-Dist: scikit-learn
Requires-Dist: packaging
Requires-Dist: jsonlines
